{
  "title": "DeepWiki-Open Documentation",
  "description": "Comprehensive documentation for the DeepWiki-Open project, detailing system architecture, features, and usage.",
  "lastIndexed": "2025-11-11",
  "toc": [
    {
      "id": "overview",
      "title": "Overview",
      "files": [
        "README.md"
      ]
    },
    {
      "id": "system-architecture",
      "title": "System Architecture",
      "children": [
        {
          "id": "core-backend-services",
          "title": "Core Backend Services",
          "files": [
            "api/main.py",
            "api/api.py",
            "api/data_pipeline.py"
          ]
        },
        {
          "id": "frontend-architecture",
          "title": "Frontend Architecture",
          "files": [
            "src/app/page.tsx",
            "src/components/Mermaid.tsx"
          ]
        },
        {
          "id": "data-processing-pipeline",
          "title": "Data Processing Pipeline",
          "files": [
            "api/data_pipeline.py"
          ]
        },
        {
          "id": "model-selection-system",
          "title": "Provider-Based Model Selection System",
          "files": [
            "README.md"
          ]
        }
      ],
      "files": [
        "api/README.md",
        "README.md"
      ]
    },
    {
      "id": "features",
      "title": "Features",
      "children": [
        {
          "id": "instant-documentation",
          "title": "Instant Documentation",
          "files": []
        },
        {
          "id": "private-repo-support",
          "title": "Private Repository Support",
          "files": []
        },
        {
          "id": "smart-analysis",
          "title": "Smart Analysis",
          "files": []
        },
        {
          "id": "ask-feature",
          "title": "Ask Feature",
          "files": []
        },
        {
          "id": "deep-research",
          "title": "DeepResearch Feature",
          "files": []
        }
      ],
      "files": [
        "README.md"
      ]
    },
    {
      "id": "data-models",
      "title": "Data Models",
      "files": [
        "api/config/embedder.json",
        "api/config/generator.json",
        "api/config/repo.json"
      ]
    },
    {
      "id": "configuration",
      "title": "Configuration",
      "files": [
        ".env",
        "docker-compose.yml"
      ]
    },
    {
      "id": "deployment",
      "title": "Deployment",
      "files": [
        "Dockerfile",
        "docker-compose.yml"
      ]
    },
    {
      "id": "observability",
      "title": "Observability",
      "files": [
        "api/logging_config.py"
      ]
    },
    {
      "id": "security-and-governance",
      "title": "Security and Governance",
      "files": [
        "README.md"
      ]
    },
    {
      "id": "troubleshooting",
      "title": "Troubleshooting",
      "files": [
        "README.md"
      ]
    },
    {
      "id": "contributing",
      "title": "Contributing",
      "files": [
        "README.md"
      ]
    },
    {
      "id": "license",
      "title": "License",
      "files": [
        "LICENSE"
      ]
    }
  ]
}